setup.py
dsnd_distributions_QianLiu_nd/Binomialdistribution.py
dsnd_distributions_QianLiu_nd/Binomialdistribution_challenge.py
dsnd_distributions_QianLiu_nd/Gaussiandistribution.py
dsnd_distributions_QianLiu_nd/Generaldistribution.py
dsnd_distributions_QianLiu_nd/__init__.py
dsnd_distributions_QianLiu_nd.egg-info/PKG-INFO
dsnd_distributions_QianLiu_nd.egg-info/SOURCES.txt
dsnd_distributions_QianLiu_nd.egg-info/dependency_links.txt
dsnd_distributions_QianLiu_nd.egg-info/not-zip-safe
dsnd_distributions_QianLiu_nd.egg-info/top_level.txt