Metadata-Version: 1.0
Name: dsnd-distributions-QianLiu-nd
Version: 0.1
Summary: Gaussian distributions and Binomial distributions
Home-page: UNKNOWN
Author: Qian Liu
Author-email: UNKNOWN
License: UNKNOWN
Platform: UNKNOWN
